nano_swe_agent-1.0.0.dev3.dist-info/licenses/LICENSE.md
nanoswea/__init__.py
nanoswea/__main__.py
nanoswea/agent.py
nanoswea/environment.py
nanoswea/model.py
nanoswea/run_github_issue.py
nanoswea/run_local.py
nanoswea/config/github_issue.yaml
nanoswea/config/local.yaml
nanoswea/config/extra/swebench.yaml
nanoswea/extra/__init__.py
nanoswea/extra/environment/swerex_docker.py
nanoswea/extra/model/test_models.py
nanoswea/extra/run/run_swebench.py
nano_swe_agent-1.0.0.dev3.dist-info/METADATA
nano_swe_agent-1.0.0.dev3.dist-info/WHEEL
nano_swe_agent-1.0.0.dev3.dist-info/entry_points.txt
nano_swe_agent-1.0.0.dev3.dist-info/top_level.txt
nano_swe_agent-1.0.0.dev3.dist-info/RECORD
