Metadata-Version: 2.4
Name: nano-swe-agent
Version: 1.0.0.dev3
Summary: Nano SWE Agent - A simple AI software engineering agent
Author-email: Kilian Lieret <kilian.lieret@posteo.de>
License: MIT License
Keywords: nlp,agents,code
Classifier: Development Status :: 3 - Alpha
Classifier: Operating System :: OS Independent
Classifier: Intended Audience :: Developers
Classifier: License :: OSI Approved :: MIT License
Classifier: Programming Language :: Python :: 3.11
Classifier: Programming Language :: Python :: 3 :: Only
Requires-Python: >=3.11
License-File: LICENSE.md
Requires-Dist: pyyaml
Requires-Dist: requests
Requires-Dist: jinja2
Requires-Dist: litellm
Requires-Dist: tenacity
Requires-Dist: datasets
Requires-Dist: rich
Requires-Dist: python-dotenv
Requires-Dist: typer
Provides-Extra: dev
Requires-Dist: pytest; extra == "dev"
Requires-Dist: pytest-cov; extra == "dev"
Requires-Dist: pre-commit; extra == "dev"
Requires-Dist: ruff; extra == "dev"
Dynamic: license-file
